pycngal/__init__.py
pycngal/__main__.py
pycngal/const.py
python_cngal-0.2.2.dist-info/LICENSE
python_cngal-0.2.2.dist-info/METADATA
python_cngal-0.2.2.dist-info/WHEEL
python_cngal-0.2.2.dist-info/RECORD
