Metadata-Version: 2.1
Name: python-cngal
Version: 0.2.2
Summary: A Python wrapper for cngal.org API
Author: 快乐的老鼠宝宝
Author-email: keaitianxinmail@qq.com
Requires-Python: >=3.8,<4.0
Classifier: Programming Language :: Python :: 3
Classifier: Programming Language :: Python :: 3.8
Classifier: Programming Language :: Python :: 3.9
Classifier: Programming Language :: Python :: 3.10
Classifier: Programming Language :: Python :: 3.11
Requires-Dist: requests (>=2.28.2,<3.0.0)
